testlambda/__init__.py
testlambda/lambda.py
testlambda-0.2.dist-info/METADATA
testlambda-0.2.dist-info/WHEEL
testlambda-0.2.dist-info/top_level.txt
testlambda-0.2.dist-info/RECORD
