Metadata-Version: 2.1
Name: testlambda
Version: 0.2
Summary: A sample Python package
Author: John Doe
Author-email: jdoe@example.com
Requires-Dist: requests
Requires-Dist: boto3
